oldap_tools/__init__.py
oldap_tools/__main__.py
oldap_tools/cli.py
oldap_tools/config.py
oldap_tools/dump_list.py
oldap_tools/dump_project.py
oldap_tools/load_list.py
oldap_tools/load_project.py
oldap_tools/logging.py
oldap_tools-0.1.4.dist-info/METADATA
oldap_tools-0.1.4.dist-info/WHEEL
oldap_tools-0.1.4.dist-info/entry_points.txt
oldap_tools-0.1.4.dist-info/RECORD
