Metadata-Version: 2.1
Name: oldap-tools
Version: 0.1.4
Summary: CLI tools for OLDAP
License: GPL-3.0-only
Author: Lukas Rosenthaler
Author-email: lukas.rosenthaler@unibas.ch
Requires-Python: >=3.11,<4.0
Classifier: License :: OSI Approved :: GNU General Public License v3 (GPLv3)
Classifier: Programming Language :: Python :: 3
Classifier: Programming Language :: Python :: 3.11
Classifier: Programming Language :: Python :: 3.12
Requires-Dist: oldaplib (>=0.4.1,<0.5.0)
Requires-Dist: rdflib (>=7.5.0,<8.0.0)
Requires-Dist: typer (>=0.20.0,<0.21.0)
